lie_transformer_pytorch/__init__.py
lie_transformer_pytorch/lie_transformer_pytorch.py
lie_transformer_pytorch/reversible.py
lie_transformer_pytorch/se3.py
lie_transformer_pytorch-0.0.17.dist-info/LICENSE
lie_transformer_pytorch-0.0.17.dist-info/METADATA
lie_transformer_pytorch-0.0.17.dist-info/WHEEL
lie_transformer_pytorch-0.0.17.dist-info/top_level.txt
lie_transformer_pytorch-0.0.17.dist-info/RECORD
